graphene_subscriptions/__init__.py
graphene_subscriptions/apps.py
graphene_subscriptions/consumers.py
graphene_subscriptions/events.py
graphene_subscriptions/signals.py
graphene_subscriptions-1.0.1.dist-info/LICENSE
graphene_subscriptions-1.0.1.dist-info/WHEEL
graphene_subscriptions-1.0.1.dist-info/METADATA
graphene_subscriptions-1.0.1.dist-info/RECORD
