Metadata-Version: 2.1
Name: graphene-subscriptions
Version: 1.0.1
Summary: A plug-and-play GraphQL subscription implementation for Graphene + Django built using Django Channels.
Home-page: https://github.com/jaydenwindle/graphene-subscriptions
License: MIT
Author: Jayden Windle
Author-email: jaydenwindle@gmail.com
Requires-Python: >=3.6
Classifier: Environment :: Web Environment
Classifier: Framework :: Django
Classifier: Framework :: Django :: 1.11
Classifier: Framework :: Django :: 2.1
Classifier: Framework :: Django :: 2.2
Classifier: Framework :: Django :: 3.0
Classifier: Intended Audience :: Developers
Classifier: License :: OSI Approved :: MIT License
Classifier: Operating System :: OS Independent
Classifier: Programming Language :: Python
Classifier: Programming Language :: Python :: 3
Classifier: Programming Language :: Python :: 3 :: Only
Classifier: Programming Language :: Python :: 3.5
Classifier: Programming Language :: Python :: 3.6
Classifier: Programming Language :: Python :: 3.7
Classifier: Programming Language :: Python :: 3.8
Classifier: Topic :: Internet :: WWW/HTTP
Classifier: Topic :: Internet :: WWW/HTTP :: Dynamic Content
Requires-Dist: channels (>=2.3,<3.0)
Requires-Dist: django (>=1.11)
Requires-Dist: graphene-django (>=2.7,<3.0)
Project-URL: Repository, https://github.com/jaydenwindle/graphene-subscriptions
